bcpo_feature_selector/__init__.py
bcpo_feature_selector/classification/__init__.py
bcpo_feature_selector/classification/metrics.py
bcpo_feature_selector/classification/selector.py
bcpo_feature_selector/regression/__init__.py
bcpo_feature_selector/regression/metrics.py
bcpo_feature_selector/regression/selector.py
bcpo_feature_selector-0.1.0.post1.dist-info/licenses/LICENSE
bcpo_feature_selector-0.1.0.post1.dist-info/METADATA
bcpo_feature_selector-0.1.0.post1.dist-info/WHEEL
bcpo_feature_selector-0.1.0.post1.dist-info/top_level.txt
bcpo_feature_selector-0.1.0.post1.dist-info/RECORD
