Metadata-Version: 2.4
Name: bcpo_feature_selector
Version: 0.1.0.post1
Summary: Binary Crested Porcupine Optimizer (BCPO) for feature selection
Author: Nguyễn Ngọc Thiện
License: MIT
Requires-Python: >=3.9
License-File: LICENSE
Requires-Dist: numpy>=1.22
Requires-Dist: scikit-learn>=1.2
Provides-Extra: dev
Requires-Dist: pytest>=7; extra == "dev"
Requires-Dist: pytest-cov; extra == "dev"
Requires-Dist: flake8; extra == "dev"
Provides-Extra: docs
Requires-Dist: sphinx>=7.0; extra == "docs"
Requires-Dist: sphinx-rtd-theme; extra == "docs"
Requires-Dist: myst-parser; extra == "docs"
Dynamic: license-file
